layoutparser/__init__.py
layoutparser/file_utils.py
layoutparser/visualization.py
layoutparser/elements/__init__.py
layoutparser/elements/base.py
layoutparser/elements/errors.py
layoutparser/elements/layout.py
layoutparser/elements/layout_elements.py
layoutparser/elements/utils.py
layoutparser/io/__init__.py
layoutparser/io/basic.py
layoutparser/io/pdf.py
layoutparser/misc/NotoSerifCJKjp-Regular.otf
layoutparser/models/__init__.py
layoutparser/models/auto_layoutmodel.py
layoutparser/models/base_catalog.py
layoutparser/models/base_layoutmodel.py
layoutparser/models/model_config.py
layoutparser/models/detectron2/__init__.py
layoutparser/models/detectron2/catalog.py
layoutparser/models/detectron2/layoutmodel.py
layoutparser/models/effdet/__init__.py
layoutparser/models/effdet/catalog.py
layoutparser/models/effdet/layoutmodel.py
layoutparser/models/paddledetection/__init__.py
layoutparser/models/paddledetection/catalog.py
layoutparser/models/paddledetection/layoutmodel.py
layoutparser/ocr/__init__.py
layoutparser/ocr/base.py
layoutparser/ocr/gcv_agent.py
layoutparser/ocr/tesseract_agent.py
layoutparser/tools/__init__.py
layoutparser/tools/shape_operations.py
layoutparser-0.3.4.dist-info/LICENSE
layoutparser-0.3.4.dist-info/METADATA
layoutparser-0.3.4.dist-info/WHEEL
layoutparser-0.3.4.dist-info/top_level.txt
layoutparser-0.3.4.dist-info/RECORD
