Metadata-Version: 2.1
Name: layoutparser
Version: 0.3.4
Summary: A unified toolkit for Deep Learning Based Document Image Analysis
Home-page: https://github.com/Layout-Parser/layout-parser
Author: Zejiang Shen, Ruochen Zhang, and Layout Parser Model Contributors
Author-email: layoutparser@gmail.com
License: Apache-2.0
Keywords: layout analysis,deep learning
Platform: UNKNOWN
Classifier: Intended Audience :: Developers
Classifier: Intended Audience :: Education
Classifier: Intended Audience :: Science/Research
Classifier: License :: OSI Approved :: Apache Software License
Classifier: Programming Language :: Python :: 3
Classifier: Programming Language :: Python :: 3.6
Classifier: Programming Language :: Python :: 3.7
Classifier: Programming Language :: Python :: 3.8
Classifier: Programming Language :: Python :: 3.9
Classifier: Topic :: Scientific/Engineering :: Artificial Intelligence
Requires-Python: >=3.6
Provides-Extra: ocr
Provides-Extra: gcv
Provides-Extra: tesseract
Provides-Extra: layoutmodels
Provides-Extra: effdet
Provides-Extra: paddledetection
License-File: LICENSE
